{
 "meta": {
  "updated": "2026-07-21",
  "fx": {
   "USD": 96.25,
   "GBP": 129.03,
   "CAD": 68.4,
   "AUD": 67.52,
   "NZD": 56.24
  }
 },
 "config": {
  "buyWithin": 0.1,
  "maybeWithin": 0.25,
  "forexPct": 0.03,
  "overheadPct": 0.1,
  "delivery": 0,
  "bgiDefaultDiscount": 0.1
 },
 "games": [
  {
   "name": "7 Wonders: Architects – Medals",
   "type": "Expansion",
   "bgoId": "aSZ_dqxVMB",
   "indiaUrl": "",
   "discount": null,
   "status": "Not Started",
   "prices": {
    "USA": 19.19,
    "UK": 19.19,
    "Canada": 19.19,
    "Australia": 19.19,
    "NZ": 19.19
   },
   "stock": {
    "USA": "In stock",
    "UK": "In stock",
    "Canada": "In stock",
    "Australia": "In stock",
    "NZ": "In stock"
   },
   "india": null
  },
  {
   "name": "Adulthood",
   "type": "Boardgame",
   "bgoId": "VhusYdGcvM",
   "indiaUrl": "",
   "discount": null,
   "status": "Not Started",
   "prices": {
    "USA": 27.99,
    "UK": 27.99,
    "Canada": 27.99,
    "Australia": 27.99,
    "NZ": 27.99
   },
   "stock": {
    "USA": "In stock",
    "UK": "In stock",
    "Canada": "In stock",
    "Australia": "In stock",
    "NZ": "In stock"
   },
   "india": null
  },
  {
   "name": "Agent Avenue",
   "type": "Boardgame",
   "bgoId": "wBRRNgnGmH",
   "indiaUrl": "",
   "discount": null,
   "status": "Not Started",
   "prices": {
    "USA": 18.39,
    "UK": 18.39,
    "Canada": 18.39,
    "Australia": 18.39,
    "NZ": 18.39
   },
   "stock": {
    "USA": "In stock",
    "UK": "In stock",
    "Canada": "In stock",
    "Australia": "In stock",
    "NZ": "In stock"
   },
   "india": null
  },
  {
   "name": "Akropolis",
   "type": "Boardgame",
   "bgoId": "18XRhCd2-R",
   "indiaUrl": "https://www.boardgamesindia.com/akropolis-gigamic",
   "discount": null,
   "status": "Not Started",
   "prices": {
    "USA": 25.49,
    "UK": 25.49,
    "Canada": 25.49,
    "Australia": 25.49,
    "NZ": 25.49
   },
   "stock": {
    "USA": "In stock",
    "UK": "In stock",
    "Canada": "In stock",
    "Australia": "In stock",
    "NZ": "In stock"
   },
   "india": {
    "price": 3000,
    "source": "Board Games India",
    "stock": "oos"
   }
  },
  {
   "name": "Avant Carde",
   "type": "Boardgame",
   "bgoId": "3a1vTFjOBP",
   "indiaUrl": "",
   "discount": null,
   "status": "Not Started",
   "prices": {
    "USA": 14.47,
    "UK": 14.47,
    "Canada": 14.47,
    "Australia": 14.47,
    "NZ": 14.47
   },
   "stock": {
    "USA": "In stock",
    "UK": "In stock",
    "Canada": "In stock",
    "Australia": "In stock",
    "NZ": "In stock"
   },
   "india": null
  },
  {
   "name": "Backstories: Alone under the Ice",
   "type": "Boardgame",
   "bgoId": "F3aqY4L33D",
   "indiaUrl": "",
   "discount": null,
   "status": "Not Started",
   "prices": {
    "USA": 13.99,
    "UK": 13.99,
    "Canada": 13.99,
    "Australia": 13.99,
    "NZ": 13.99
   },
   "stock": {
    "USA": "In stock",
    "UK": "In stock",
    "Canada": "In stock",
    "Australia": "In stock",
    "NZ": "In stock"
   },
   "india": null
  },
  {
   "name": "Betrayal at House on the Hill: 3rd Edition",
   "type": "Boardgame",
   "bgoId": "xpbQrCbx0n",
   "indiaUrl": "https://www.boardgamesindia.com/on-demand/betrayal-at-house-on-the-hill-3rd-edition-avalon-hill",
   "discount": null,
   "status": "Not Started",
   "prices": {
    "USA": 46.97,
    "UK": 46.97,
    "Canada": 46.97,
    "Australia": 46.97,
    "NZ": 46.97
   },
   "stock": {
    "USA": "In stock",
    "UK": "In stock",
    "Canada": "In stock",
    "Australia": "In stock",
    "NZ": "In stock"
   },
   "india": {
    "price": 9999,
    "source": "Board Games India",
    "stock": "oos"
   }
  },
  {
   "name": "Between Two Castles Essential Edition",
   "type": "Boardgame",
   "bgoId": "y7iGBdn-Ii",
   "indiaUrl": "",
   "discount": null,
   "status": "Not Started",
   "prices": {
    "USA": 40,
    "UK": 40,
    "Canada": 40,
    "Australia": 40,
    "NZ": 40
   },
   "stock": {
    "USA": "In stock",
    "UK": "In stock",
    "Canada": "In stock",
    "Australia": "In stock",
    "NZ": "In stock"
   },
   "india": null
  },
  {
   "name": "Bites",
   "type": "Boardgame",
   "bgoId": "pZP0fG-0lz",
   "indiaUrl": "",
   "discount": null,
   "status": "Not Started",
   "prices": {
    "USA": 22.95,
    "UK": 22.95,
    "Canada": 22.95,
    "Australia": 22.95,
    "NZ": 22.95
   },
   "stock": {
    "USA": "In stock",
    "UK": "In stock",
    "Canada": "In stock",
    "Australia": "In stock",
    "NZ": "In stock"
   },
   "india": null
  },
  {
   "name": "Burgle Bros 2: The Casino Capers",
   "type": "Boardgame",
   "bgoId": "nbQEbvWkTy",
   "indiaUrl": "",
   "discount": null,
   "status": "Not Started",
   "prices": {
    "USA": null,
    "UK": null,
    "Canada": 75.99,
    "Australia": 67.95,
    "NZ": 81.3235113
   },
   "stock": {
    "USA": "",
    "UK": "",
    "Canada": "In stock",
    "Australia": "In stock",
    "NZ": "In stock"
   },
   "india": null
  },
  {
   "name": "Caesar!: Seize Rome in 20 minutes",
   "type": "Boardgame",
   "bgoId": "GYII4RVfZb",
   "indiaUrl": "",
   "discount": null,
   "status": "Not Started",
   "prices": {
    "USA": 24.99,
    "UK": 24.99,
    "Canada": 24.99,
    "Australia": 24.99,
    "NZ": 24.99
   },
   "stock": {
    "USA": "In stock",
    "UK": "In stock",
    "Canada": "In stock",
    "Australia": "In stock",
    "NZ": "In stock"
   },
   "india": null
  },
  {
   "name": "Caper: Europe",
   "type": "Boardgame",
   "bgoId": "UbaMKhiLmk",
   "indiaUrl": "",
   "discount": null,
   "status": "Not Started",
   "prices": {
    "USA": 34.99,
    "UK": 34.99,
    "Canada": 34.99,
    "Australia": 34.99,
    "NZ": 34.99
   },
   "stock": {
    "USA": "In stock",
    "UK": "In stock",
    "Canada": "In stock",
    "Australia": "In stock",
    "NZ": "In stock"
   },
   "india": null
  },
  {
   "name": "Capital Lux 2: Generations",
   "type": "Boardgame",
   "bgoId": "xM7wkfU6Us",
   "indiaUrl": "",
   "discount": null,
   "status": "Not Started",
   "prices": {
    "USA": 28,
    "UK": 28,
    "Canada": 28,
    "Australia": 28,
    "NZ": 28
   },
   "stock": {
    "USA": "Out of stock",
    "UK": "Out of stock",
    "Canada": "Out of stock",
    "Australia": "Out of stock",
    "NZ": "Out of stock"
   },
   "india": null
  },
  {
   "name": "Captain Flip",
   "type": "Boardgame",
   "bgoId": "rN_LDV4ctI",
   "indiaUrl": "https://www.boardgamesindia.com/captain-flip",
   "discount": null,
   "status": "Not Started",
   "prices": {
    "USA": 19.96,
    "UK": 19.96,
    "Canada": 19.96,
    "Australia": 19.96,
    "NZ": 19.96
   },
   "stock": {
    "USA": "Out of stock",
    "UK": "Out of stock",
    "Canada": "Out of stock",
    "Australia": "Out of stock",
    "NZ": "Out of stock"
   },
   "india": null
  },
  {
   "name": "Cartographers",
   "type": "Boardgame",
   "bgoId": "cM4QCD3zYX",
   "indiaUrl": "https://www.boardgamesindia.com/cartographers-thunderworks-games",
   "discount": null,
   "status": "Not Started",
   "prices": {
    "USA": 19.99,
    "UK": 19.99,
    "Canada": 19.99,
    "Australia": 19.99,
    "NZ": 19.99
   },
   "stock": {
    "USA": "In stock",
    "UK": "In stock",
    "Canada": "In stock",
    "Australia": "In stock",
    "NZ": "In stock"
   },
   "india": {
    "price": 2800,
    "source": "Board Games India",
    "stock": "oos"
   }
  },
  {
   "name": "Cascadia",
   "type": "Boardgame",
   "bgoId": "12975B7EQh",
   "indiaUrl": "https://www.boardgamesindia.com/cascadia-retail-edition-flatout-games",
   "discount": null,
   "status": "Not Started",
   "prices": {
    "USA": 31.99,
    "UK": 31.99,
    "Canada": 31.99,
    "Australia": 31.99,
    "NZ": 31.99
   },
   "stock": {
    "USA": "In stock",
    "UK": "In stock",
    "Canada": "In stock",
    "Australia": "In stock",
    "NZ": "In stock"
   },
   "india": {
    "price": 3300,
    "source": "Board Games India",
    "stock": "In stock"
   }
  },
  {
   "name": "Chit Chat",
   "type": "Boardgame",
   "bgoId": "-3AFvRFHBr",
   "indiaUrl": "",
   "discount": null,
   "status": "Not Started",
   "prices": {
    "USA": 17.59,
    "UK": 17.59,
    "Canada": 17.59,
    "Australia": 17.59,
    "NZ": 17.59
   },
   "stock": {
    "USA": "In stock",
    "UK": "In stock",
    "Canada": "In stock",
    "Australia": "In stock",
    "NZ": "In stock"
   },
   "india": null
  },
  {
   "name": "Clank!: Catacombs",
   "type": "Boardgame",
   "bgoId": "riDpYrS7rp",
   "indiaUrl": "https://www.boardgamesindia.com/clank-catacombs-dire-wolf",
   "discount": null,
   "status": "Not Started",
   "prices": {
    "USA": 59.99,
    "UK": 59.99,
    "Canada": 59.99,
    "Australia": 59.99,
    "NZ": 59.99
   },
   "stock": {
    "USA": "In stock",
    "UK": "In stock",
    "Canada": "In stock",
    "Australia": "In stock",
    "NZ": "In stock"
   },
   "india": {
    "price": 6500,
    "source": "Board Games India",
    "stock": "oos"
   }
  },
  {
   "name": "Colt Express: Couriers & Armored Train",
   "type": "Expansion",
   "bgoId": "TxiXaMhQQ5",
   "indiaUrl": "",
   "discount": null,
   "status": "Not Started",
   "prices": {
    "USA": 25.83,
    "UK": 25.83,
    "Canada": 25.83,
    "Australia": 25.83,
    "NZ": 25.83
   },
   "stock": {
    "USA": "In stock",
    "UK": "In stock",
    "Canada": "In stock",
    "Australia": "In stock",
    "NZ": "In stock"
   },
   "india": null
  },
  {
   "name": "Dabba Walla",
   "type": "Boardgame",
   "bgoId": "Y-JRgoah_t",
   "indiaUrl": "",
   "discount": null,
   "status": "Not Started",
   "prices": {
    "USA": 31.97,
    "UK": 31.97,
    "Canada": 31.97,
    "Australia": 31.97,
    "NZ": 31.97
   },
   "stock": {
    "USA": "In stock",
    "UK": "In stock",
    "Canada": "In stock",
    "Australia": "In stock",
    "NZ": "In stock"
   },
   "india": null
  },
  {
   "name": "Décorum",
   "type": "Boardgame",
   "bgoId": "bVpuXqrPqp",
   "indiaUrl": "",
   "discount": null,
   "status": "Not Started",
   "prices": {
    "USA": 28.97,
    "UK": 28.97,
    "Canada": 28.97,
    "Australia": 28.97,
    "NZ": 28.97
   },
   "stock": {
    "USA": "In stock",
    "UK": "In stock",
    "Canada": "In stock",
    "Australia": "In stock",
    "NZ": "In stock"
   },
   "india": null
  },
  {
   "name": "Decrypto: Expansion #01 – Laserdrive",
   "type": "Expansion",
   "bgoId": "gv4cb-vT20",
   "indiaUrl": "",
   "discount": null,
   "status": "Not Started",
   "prices": {
    "USA": 11.99,
    "UK": 11.99,
    "Canada": 11.99,
    "Australia": 11.99,
    "NZ": 11.99
   },
   "stock": {
    "USA": "Out of stock",
    "UK": "Out of stock",
    "Canada": "Out of stock",
    "Australia": "Out of stock",
    "NZ": "Out of stock"
   },
   "india": null
  },
  {
   "name": "Detective Club",
   "type": "Boardgame",
   "bgoId": "nXRwUjoIza",
   "indiaUrl": "",
   "discount": null,
   "status": "Not Started",
   "prices": {
    "USA": 28.97,
    "UK": 28.97,
    "Canada": 28.97,
    "Australia": 28.97,
    "NZ": 28.97
   },
   "stock": {
    "USA": "Out of stock",
    "UK": "Out of stock",
    "Canada": "Out of stock",
    "Australia": "Out of stock",
    "NZ": "Out of stock"
   },
   "india": null
  },
  {
   "name": "Dorfromantik: The Board Game",
   "type": "Boardgame",
   "bgoId": "ZMnXUYGRJV",
   "indiaUrl": "https://www.boardgamesindia.com/dorfromantik-the-board-game-pegasus-spiele",
   "discount": null,
   "status": "Not Started",
   "prices": {
    "USA": 31.47,
    "UK": 31.47,
    "Canada": 31.47,
    "Australia": 31.47,
    "NZ": 31.47
   },
   "stock": {
    "USA": "In stock",
    "UK": "In stock",
    "Canada": "In stock",
    "Australia": "In stock",
    "NZ": "In stock"
   },
   "india": {
    "price": 4000,
    "source": "Board Games India",
    "stock": "oos"
   }
  },
  {
   "name": "Draftosaurus",
   "type": "Boardgame",
   "bgoId": "1fceNlC8dC",
   "indiaUrl": "https://www.boardgamesindia.com/draftosaurus",
   "discount": null,
   "status": "Not Started",
   "prices": {
    "USA": 17.99,
    "UK": 17.99,
    "Canada": 17.99,
    "Australia": 17.99,
    "NZ": 17.99
   },
   "stock": {
    "USA": "Out of stock",
    "UK": "Out of stock",
    "Canada": "Out of stock",
    "Australia": "Out of stock",
    "NZ": "Out of stock"
   },
   "india": {
    "price": 2499,
    "source": "Board Games India",
    "stock": "oos"
   }
  },
  {
   "name": "Dying Message",
   "type": "Boardgame",
   "bgoId": "GQFKAzsekJ",
   "indiaUrl": "",
   "discount": null,
   "status": "Not Started",
   "prices": {
    "USA": 22.47,
    "UK": 22.47,
    "Canada": 22.47,
    "Australia": 22.47,
    "NZ": 22.47
   },
   "stock": {
    "USA": "In stock",
    "UK": "In stock",
    "Canada": "In stock",
    "Australia": "In stock",
    "NZ": "In stock"
   },
   "india": null
  },
  {
   "name": "Faraway: People From Below",
   "type": "Expansion",
   "bgoId": "yTlhANq11R",
   "indiaUrl": "",
   "discount": null,
   "status": "Not Started",
   "prices": {
    "USA": 6.99,
    "UK": 6.99,
    "Canada": 6.99,
    "Australia": 6.99,
    "NZ": 6.99
   },
   "stock": {
    "USA": "In stock",
    "UK": "In stock",
    "Canada": "In stock",
    "Australia": "In stock",
    "NZ": "In stock"
   },
   "india": null
  },
  {
   "name": "Final Girl: Frightmare on Maple Lane",
   "type": "Expansion",
   "bgoId": "M4zlQnkXA0",
   "indiaUrl": "",
   "discount": null,
   "status": "Not Started",
   "prices": {
    "USA": 19.99,
    "UK": 19.99,
    "Canada": 19.99,
    "Australia": 19.99,
    "NZ": 19.99
   },
   "stock": {
    "USA": "In stock",
    "UK": "In stock",
    "Canada": "In stock",
    "Australia": "In stock",
    "NZ": "In stock"
   },
   "india": null
  },
  {
   "name": "Fireball Island: Race to Adventure",
   "type": "Boardgame",
   "bgoId": "Oe64uTQ1Sf",
   "indiaUrl": "",
   "discount": null,
   "status": "Not Started",
   "prices": {
    "USA": null,
    "UK": null,
    "Canada": 37.94,
    "Australia": null,
    "NZ": null
   },
   "stock": {
    "USA": "",
    "UK": "",
    "Canada": "In stock",
    "Australia": "",
    "NZ": ""
   },
   "india": null
  },
  {
   "name": "Forest Shuffle",
   "type": "Boardgame",
   "bgoId": "eJORAg6hls",
   "indiaUrl": "https://www.boardgamesindia.com/forest-shuffle",
   "discount": null,
   "status": "Not Started",
   "prices": {
    "USA": 23.99,
    "UK": 23.99,
    "Canada": 23.99,
    "Australia": 23.99,
    "NZ": 23.99
   },
   "stock": {
    "USA": "In stock",
    "UK": "In stock",
    "Canada": "In stock",
    "Australia": "In stock",
    "NZ": "In stock"
   },
   "india": {
    "price": 3000,
    "source": "Board Games India",
    "stock": "oos"
   }
  },
  {
   "name": "Foundations of Metropolis",
   "type": "Boardgame",
   "bgoId": "6NQptWjOyw",
   "indiaUrl": "",
   "discount": null,
   "status": "Not Started",
   "prices": {
    "USA": 32.33,
    "UK": 32.33,
    "Canada": 32.33,
    "Australia": 32.33,
    "NZ": 32.33
   },
   "stock": {
    "USA": "In stock",
    "UK": "In stock",
    "Canada": "In stock",
    "Australia": "In stock",
    "NZ": "In stock"
   },
   "india": null
  },
  {
   "name": "Fugitive (Second Edition)",
   "type": "Boardgame",
   "bgoId": "FJaY49WWt8",
   "indiaUrl": "",
   "discount": null,
   "status": "Not Started",
   "prices": {
    "USA": 25.82,
    "UK": 25.82,
    "Canada": 25.82,
    "Australia": 25.82,
    "NZ": 25.82
   },
   "stock": {
    "USA": "In stock",
    "UK": "In stock",
    "Canada": "In stock",
    "Australia": "In stock",
    "NZ": "In stock"
   },
   "india": null
  },
  {
   "name": "Hamster roll",
   "type": "Boardgame",
   "bgoId": "KJoCBILA6M",
   "indiaUrl": "",
   "discount": null,
   "status": "Not Started",
   "prices": {
    "USA": 35.99,
    "UK": 35.99,
    "Canada": 35.99,
    "Australia": 35.99,
    "NZ": 35.99
   },
   "stock": {
    "USA": "In stock",
    "UK": "In stock",
    "Canada": "In stock",
    "Australia": "In stock",
    "NZ": "In stock"
   },
   "india": null
  },
  {
   "name": "Harmonies",
   "type": "Boardgame",
   "bgoId": "46AnulxktA",
   "indiaUrl": "https://www.boardgamesindia.com/harmonies",
   "discount": null,
   "status": "Not Started",
   "prices": {
    "USA": 31.99,
    "UK": 31.99,
    "Canada": 31.99,
    "Australia": 31.99,
    "NZ": 31.99
   },
   "stock": {
    "USA": "In stock",
    "UK": "In stock",
    "Canada": "In stock",
    "Australia": "In stock",
    "NZ": "In stock"
   },
   "india": {
    "price": 3800,
    "source": "Board Games India",
    "stock": "In stock"
   }
  },
  {
   "name": "Heat: Heavy Rain",
   "type": "Expansion",
   "bgoId": "8Dp1ru1HKU",
   "indiaUrl": "",
   "discount": null,
   "status": "Not Started",
   "prices": {
    "USA": 26.89,
    "UK": 26.89,
    "Canada": 26.89,
    "Australia": 26.89,
    "NZ": 26.89
   },
   "stock": {
    "USA": "In stock",
    "UK": "In stock",
    "Canada": "In stock",
    "Australia": "In stock",
    "NZ": "In stock"
   },
   "india": null
  },
  {
   "name": "Heat: Tunnel Vision",
   "type": "Expansion",
   "bgoId": "umdb8GC1kw",
   "indiaUrl": "",
   "discount": null,
   "status": "Not Started",
   "prices": {
    "USA": 30.39,
    "UK": 30.39,
    "Canada": 30.39,
    "Australia": 30.39,
    "NZ": 30.39
   },
   "stock": {
    "USA": "In stock",
    "UK": "In stock",
    "Canada": "In stock",
    "Australia": "In stock",
    "NZ": "In stock"
   },
   "india": null
  },
  {
   "name": "High Society",
   "type": "Boardgame",
   "bgoId": "q2p8_Jtk8p",
   "indiaUrl": "https://www.boardgamesindia.com/high-society",
   "discount": null,
   "status": "Not Started",
   "prices": {
    "USA": 19.47,
    "UK": 19.47,
    "Canada": 19.47,
    "Australia": 19.47,
    "NZ": 19.47
   },
   "stock": {
    "USA": "Out of stock",
    "UK": "Out of stock",
    "Canada": "Out of stock",
    "Australia": "Out of stock",
    "NZ": "Out of stock"
   },
   "india": {
    "price": 2199,
    "source": "Board Games India",
    "stock": "oos"
   }
  },
  {
   "name": "HITSTER",
   "type": "Boardgame",
   "bgoId": "U6MaWmKnTQ",
   "indiaUrl": "",
   "discount": null,
   "status": "Not Started",
   "prices": {
    "USA": 19.82,
    "UK": 19.82,
    "Canada": 19.82,
    "Australia": 19.82,
    "NZ": 19.82
   },
   "stock": {
    "USA": "In stock",
    "UK": "In stock",
    "Canada": "In stock",
    "Australia": "In stock",
    "NZ": "In stock"
   },
   "india": null
  },
  {
   "name": "Hive",
   "type": "Boardgame",
   "bgoId": "aAss5Dqr0N",
   "indiaUrl": "",
   "discount": null,
   "status": "Not Started",
   "prices": {
    "USA": 33.99,
    "UK": 33.99,
    "Canada": 33.99,
    "Australia": 33.99,
    "NZ": 33.99
   },
   "stock": {
    "USA": "In stock",
    "UK": "In stock",
    "Canada": "In stock",
    "Australia": "In stock",
    "NZ": "In stock"
   },
   "india": null
  },
  {
   "name": "Horrified",
   "type": "Boardgame",
   "bgoId": "7jJoa7DmUY",
   "indiaUrl": "",
   "discount": null,
   "status": "Not Started",
   "prices": {
    "USA": 35.69,
    "UK": 35.69,
    "Canada": 35.69,
    "Australia": 35.69,
    "NZ": 35.69
   },
   "stock": {
    "USA": "In stock",
    "UK": "In stock",
    "Canada": "In stock",
    "Australia": "In stock",
    "NZ": "In stock"
   },
   "india": null
  },
  {
   "name": "I C E: Second Edition",
   "type": "Boardgame",
   "bgoId": "r1S2gAP8lc",
   "indiaUrl": "",
   "discount": null,
   "status": "Not Started",
   "prices": {
    "USA": null,
    "UK": null,
    "Canada": null,
    "Australia": null,
    "NZ": null
   },
   "stock": {
    "USA": "",
    "UK": "",
    "Canada": "",
    "Australia": "",
    "NZ": ""
   },
   "india": null
  },
  {
   "name": "Insider Black",
   "type": "Boardgame",
   "bgoId": "HDZs2wRXcD",
   "indiaUrl": "",
   "discount": null,
   "status": "Not Started",
   "prices": {
    "USA": 16.79,
    "UK": 16.79,
    "Canada": 16.79,
    "Australia": 16.79,
    "NZ": 16.79
   },
   "stock": {
    "USA": "Out of stock",
    "UK": "Out of stock",
    "Canada": "Out of stock",
    "Australia": "Out of stock",
    "NZ": "Out of stock"
   },
   "india": null
  },
  {
   "name": "Jamaica",
   "type": "Boardgame",
   "bgoId": "bnvj13nU00",
   "indiaUrl": "",
   "discount": null,
   "status": "Not Started",
   "prices": {
    "USA": 29.96,
    "UK": 29.96,
    "Canada": 29.96,
    "Australia": 29.96,
    "NZ": 29.96
   },
   "stock": {
    "USA": "In stock",
    "UK": "In stock",
    "Canada": "In stock",
    "Australia": "In stock",
    "NZ": "In stock"
   },
   "india": null
  },
  {
   "name": "Junk Art",
   "type": "Boardgame",
   "bgoId": "Rym1_pFaGi",
   "indiaUrl": "",
   "discount": null,
   "status": "Not Started",
   "prices": {
    "USA": 37.99,
    "UK": 37.99,
    "Canada": 37.99,
    "Australia": 37.99,
    "NZ": 37.99
   },
   "stock": {
    "USA": "Out of stock",
    "UK": "Out of stock",
    "Canada": "Out of stock",
    "Australia": "Out of stock",
    "NZ": "Out of stock"
   },
   "india": null
  },
  {
   "name": "Kabuto Sumo",
   "type": "Boardgame",
   "bgoId": "iwtYx8_nB7",
   "indiaUrl": "",
   "discount": null,
   "status": "Not Started",
   "prices": {
    "USA": 30.49,
    "UK": 30.49,
    "Canada": 30.49,
    "Australia": 30.49,
    "NZ": 30.49
   },
   "stock": {
    "USA": "In stock",
    "UK": "In stock",
    "Canada": "In stock",
    "Australia": "In stock",
    "NZ": "In stock"
   },
   "india": null
  },
  {
   "name": "Kariba",
   "type": "Boardgame",
   "bgoId": "oKlmWbaP3X",
   "indiaUrl": "",
   "discount": null,
   "status": "Not Started",
   "prices": {
    "USA": 11.99,
    "UK": 11.99,
    "Canada": 11.99,
    "Australia": 11.99,
    "NZ": 11.99
   },
   "stock": {
    "USA": "In stock",
    "UK": "In stock",
    "Canada": "In stock",
    "Australia": "In stock",
    "NZ": "In stock"
   },
   "india": null
  },
  {
   "name": "King of 12",
   "type": "Boardgame",
   "bgoId": "S23hLcaYIy",
   "indiaUrl": "",
   "discount": null,
   "status": "Not Started",
   "prices": {
    "USA": 15.99,
    "UK": 15.99,
    "Canada": 15.99,
    "Australia": 15.99,
    "NZ": 15.99
   },
   "stock": {
    "USA": "In stock",
    "UK": "In stock",
    "Canada": "In stock",
    "Australia": "In stock",
    "NZ": "In stock"
   },
   "india": null
  },
  {
   "name": "L.L.A.M.A.",
   "type": "Boardgame",
   "bgoId": "Kk9gzvsyuV",
   "indiaUrl": "",
   "discount": null,
   "status": "Not Started",
   "prices": {
    "USA": 7.99,
    "UK": 7.99,
    "Canada": 7.99,
    "Australia": 7.99,
    "NZ": 7.99
   },
   "stock": {
    "USA": "In stock",
    "UK": "In stock",
    "Canada": "In stock",
    "Australia": "In stock",
    "NZ": "In stock"
   },
   "india": null
  },
  {
   "name": "Landmarks",
   "type": "Boardgame",
   "bgoId": "_G3h_8pnYa",
   "indiaUrl": "",
   "discount": null,
   "status": "Not Started",
   "prices": {
    "USA": 19.96,
    "UK": 19.96,
    "Canada": 19.96,
    "Australia": 19.96,
    "NZ": 19.96
   },
   "stock": {
    "USA": "In stock",
    "UK": "In stock",
    "Canada": "In stock",
    "Australia": "In stock",
    "NZ": "In stock"
   },
   "india": null
  },
  {
   "name": "Lightning Train",
   "type": "Boardgame",
   "bgoId": "89DOY2jcx6",
   "indiaUrl": "",
   "discount": null,
   "status": "Not Started",
   "prices": {
    "USA": 54.99,
    "UK": 54.99,
    "Canada": 54.99,
    "Australia": 54.99,
    "NZ": 54.99
   },
   "stock": {
    "USA": "In stock",
    "UK": "In stock",
    "Canada": "In stock",
    "Australia": "In stock",
    "NZ": "In stock"
   },
   "india": null
  },
  {
   "name": "Lost Cities: The Board Game",
   "type": "Boardgame",
   "bgoId": "GAekRFN9sG",
   "indiaUrl": "",
   "discount": null,
   "status": "Not Started",
   "prices": {
    "USA": 28.99,
    "UK": 28.99,
    "Canada": 28.99,
    "Australia": 28.99,
    "NZ": 28.99
   },
   "stock": {
    "USA": "Out of stock",
    "UK": "Out of stock",
    "Canada": "Out of stock",
    "Australia": "Out of stock",
    "NZ": "Out of stock"
   },
   "india": null
  },
  {
   "name": "Machi Koro 2",
   "type": "Boardgame",
   "bgoId": "kPUcQKbX5-",
   "indiaUrl": "",
   "discount": null,
   "status": "Not Started",
   "prices": {
    "USA": 21.65,
    "UK": 21.65,
    "Canada": 21.65,
    "Australia": 21.65,
    "NZ": 21.65
   },
   "stock": {
    "USA": "In stock",
    "UK": "In stock",
    "Canada": "In stock",
    "Australia": "In stock",
    "NZ": "In stock"
   },
   "india": null
  },
  {
   "name": "MicroMacro: Crime City – All In",
   "type": "Boardgame",
   "bgoId": "7ozXTDruBu",
   "indiaUrl": "",
   "discount": null,
   "status": "Not Started",
   "prices": {
    "USA": 23.49,
    "UK": 23.49,
    "Canada": 23.49,
    "Australia": 23.49,
    "NZ": 23.49
   },
   "stock": {
    "USA": "In stock",
    "UK": "In stock",
    "Canada": "In stock",
    "Australia": "In stock",
    "NZ": "In stock"
   },
   "india": null
  },
  {
   "name": "MicroMacro: Crime City – Bonus Box",
   "type": "Expansion",
   "bgoId": "JUFrYwEjOV",
   "indiaUrl": "",
   "discount": null,
   "status": "Not Started",
   "prices": {
    "USA": 10.99,
    "UK": 10.99,
    "Canada": 10.99,
    "Australia": 10.99,
    "NZ": 10.99
   },
   "stock": {
    "USA": "In stock",
    "UK": "In stock",
    "Canada": "In stock",
    "Australia": "In stock",
    "NZ": "In stock"
   },
   "india": null
  },
  {
   "name": "MicroMacro: Crime City – Full House",
   "type": "Boardgame",
   "bgoId": "xoC2flPYiv",
   "indiaUrl": "",
   "discount": null,
   "status": "Not Started",
   "prices": {
    "USA": 34.99,
    "UK": 34.99,
    "Canada": 34.99,
    "Australia": 34.99,
    "NZ": 34.99
   },
   "stock": {
    "USA": "In stock",
    "UK": "In stock",
    "Canada": "In stock",
    "Australia": "In stock",
    "NZ": "In stock"
   },
   "india": null
  },
  {
   "name": "MicroMacro: Crime City – Showdown",
   "type": "Boardgame",
   "bgoId": "qacsfwiNez",
   "indiaUrl": "",
   "discount": null,
   "status": "Not Started",
   "prices": {
    "USA": 19.99,
    "UK": 19.99,
    "Canada": 19.99,
    "Australia": 19.99,
    "NZ": 19.99
   },
   "stock": {
    "USA": "In stock",
    "UK": "In stock",
    "Canada": "In stock",
    "Australia": "In stock",
    "NZ": "In stock"
   },
   "india": null
  },
  {
   "name": "Moon Colony Bloodbath",
   "type": "Boardgame",
   "bgoId": "aXr_Y0bTIh",
   "indiaUrl": "",
   "discount": null,
   "status": "Not Started",
   "prices": {
    "USA": 35.99,
    "UK": 35.99,
    "Canada": 35.99,
    "Australia": 35.99,
    "NZ": 35.99
   },
   "stock": {
    "USA": "In stock",
    "UK": "In stock",
    "Canada": "In stock",
    "Australia": "In stock",
    "NZ": "In stock"
   },
   "india": null
  },
  {
   "name": "Moonrollers",
   "type": "Boardgame",
   "bgoId": "Kvt2a5YkYe",
   "indiaUrl": "",
   "discount": null,
   "status": "Not Started",
   "prices": {
    "USA": 29.99,
    "UK": 29.99,
    "Canada": 29.99,
    "Australia": 29.99,
    "NZ": 29.99
   },
   "stock": {
    "USA": "In stock",
    "UK": "In stock",
    "Canada": "In stock",
    "Australia": "In stock",
    "NZ": "In stock"
   },
   "india": null
  },
  {
   "name": "Muffin Time: Pie Flavour Pack",
   "type": "Expansion",
   "bgoId": "XR74vm95Z0",
   "indiaUrl": "",
   "discount": null,
   "status": "Not Started",
   "prices": {
    "USA": null,
    "UK": null,
    "Canada": null,
    "Australia": null,
    "NZ": null
   },
   "stock": {
    "USA": "",
    "UK": "",
    "Canada": "",
    "Australia": "",
    "NZ": ""
   },
   "india": null
  },
  {
   "name": "Muffin Time: Rainbow Pack",
   "type": "Expansion",
   "bgoId": "xzjAbjTZsV",
   "indiaUrl": "",
   "discount": null,
   "status": "Not Started",
   "prices": {
    "USA": null,
    "UK": null,
    "Canada": null,
    "Australia": null,
    "NZ": null
   },
   "stock": {
    "USA": "",
    "UK": "",
    "Canada": "",
    "Australia": "",
    "NZ": ""
   },
   "india": null
  },
  {
   "name": "Nidavellir: Thingvellir",
   "type": "Expansion",
   "bgoId": "yCgBYEpo2M",
   "indiaUrl": "",
   "discount": null,
   "status": "Not Started",
   "prices": {
    "USA": 17.99,
    "UK": 17.99,
    "Canada": 17.99,
    "Australia": 17.99,
    "NZ": 17.99
   },
   "stock": {
    "USA": "In stock",
    "UK": "In stock",
    "Canada": "In stock",
    "Australia": "In stock",
    "NZ": "In stock"
   },
   "india": null
  },
  {
   "name": "Parks (Second Edition)",
   "type": "Boardgame",
   "bgoId": "x6KKLTxyag",
   "indiaUrl": "",
   "discount": null,
   "status": "Not Started",
   "prices": {
    "USA": 59.99,
    "UK": 59.99,
    "Canada": 59.99,
    "Australia": 59.99,
    "NZ": 59.99
   },
   "stock": {
    "USA": "In stock",
    "UK": "In stock",
    "Canada": "In stock",
    "Australia": "In stock",
    "NZ": "In stock"
   },
   "india": null
  },
  {
   "name": "Patchwork: Automa",
   "type": "Expansion",
   "bgoId": "S8E-AHa5bs",
   "indiaUrl": "",
   "discount": null,
   "status": "Not Started",
   "prices": {
    "USA": null,
    "UK": null,
    "Canada": null,
    "Australia": null,
    "NZ": null
   },
   "stock": {
    "USA": "",
    "UK": "",
    "Canada": "",
    "Australia": "",
    "NZ": ""
   },
   "india": null
  },
  {
   "name": "Pirates of Maracaibo",
   "type": "Boardgame",
   "bgoId": "9Wp7HZmBw1",
   "indiaUrl": "",
   "discount": null,
   "status": "Not Started",
   "prices": {
    "USA": 39.99,
    "UK": 39.99,
    "Canada": 39.99,
    "Australia": 39.99,
    "NZ": 39.99
   },
   "stock": {
    "USA": "In stock",
    "UK": "In stock",
    "Canada": "In stock",
    "Australia": "In stock",
    "NZ": "In stock"
   },
   "india": null
  },
  {
   "name": "Planet Unknown",
   "type": "Boardgame",
   "bgoId": "671dyiG6Dw",
   "indiaUrl": "",
   "discount": null,
   "status": "Not Started",
   "prices": {
    "USA": 50.12,
    "UK": 50.12,
    "Canada": 50.12,
    "Australia": 50.12,
    "NZ": 50.12
   },
   "stock": {
    "USA": "In stock",
    "UK": "In stock",
    "Canada": "In stock",
    "Australia": "In stock",
    "NZ": "In stock"
   },
   "india": null
  },
  {
   "name": "Point City",
   "type": "Boardgame",
   "bgoId": "kgox9xGtaa",
   "indiaUrl": "",
   "discount": null,
   "status": "Not Started",
   "prices": {
    "USA": 19.89,
    "UK": 19.89,
    "Canada": 19.89,
    "Australia": 19.89,
    "NZ": 19.89
   },
   "stock": {
    "USA": "In stock",
    "UK": "In stock",
    "Canada": "In stock",
    "Australia": "In stock",
    "NZ": "In stock"
   },
   "india": null
  },
  {
   "name": "Project L: Ambassador Pack",
   "type": "Expansion",
   "bgoId": "lee7ScvCA8",
   "indiaUrl": "",
   "discount": null,
   "status": "Not Started",
   "prices": {
    "USA": null,
    "UK": null,
    "Canada": null,
    "Australia": null,
    "NZ": null
   },
   "stock": {
    "USA": "",
    "UK": "",
    "Canada": "",
    "Australia": "",
    "NZ": ""
   },
   "india": null
  },
  {
   "name": "Project L: Finesse",
   "type": "Expansion",
   "bgoId": "5CLo4CbUVE",
   "indiaUrl": "",
   "discount": null,
   "status": "Not Started",
   "prices": {
    "USA": 13.59,
    "UK": 13.59,
    "Canada": 13.59,
    "Australia": 13.59,
    "NZ": 13.59
   },
   "stock": {
    "USA": "In stock",
    "UK": "In stock",
    "Canada": "In stock",
    "Australia": "In stock",
    "NZ": "In stock"
   },
   "india": null
  },
  {
   "name": "Project L: Finesse Ambassador Pack",
   "type": "Expansion",
   "bgoId": "mt8LqFekUq",
   "indiaUrl": "",
   "discount": null,
   "status": "Not Started",
   "prices": {
    "USA": null,
    "UK": null,
    "Canada": null,
    "Australia": null,
    "NZ": null
   },
   "stock": {
    "USA": "",
    "UK": "",
    "Canada": "",
    "Australia": "",
    "NZ": ""
   },
   "india": null
  },
  {
   "name": "Quacks",
   "type": "Boardgame",
   "bgoId": "bD0EsHvlcZ",
   "indiaUrl": "",
   "discount": null,
   "status": "Not Started",
   "prices": {
    "USA": 35.99,
    "UK": 35.99,
    "Canada": 35.99,
    "Australia": 35.99,
    "NZ": 35.99
   },
   "stock": {
    "USA": "In stock",
    "UK": "In stock",
    "Canada": "In stock",
    "Australia": "In stock",
    "NZ": "In stock"
   },
   "india": null
  },
  {
   "name": "Quest",
   "type": "Boardgame",
   "bgoId": "_OrAkB0VOY",
   "indiaUrl": "",
   "discount": null,
   "status": "Not Started",
   "prices": {
    "USA": null,
    "UK": null,
    "Canada": null,
    "Australia": null,
    "NZ": null
   },
   "stock": {
    "USA": "",
    "UK": "",
    "Canada": "",
    "Australia": "",
    "NZ": ""
   },
   "india": null
  },
  {
   "name": "Ra",
   "type": "Boardgame",
   "bgoId": "ztzt3fy553",
   "indiaUrl": "",
   "discount": null,
   "status": "Not Started",
   "prices": {
    "USA": 109.97,
    "UK": 109.97,
    "Canada": 109.97,
    "Australia": 109.97,
    "NZ": 109.97
   },
   "stock": {
    "USA": "In stock",
    "UK": "In stock",
    "Canada": "In stock",
    "Australia": "In stock",
    "NZ": "In stock"
   },
   "india": null
  },
  {
   "name": "Railroad Ink: Deep Blue Edition",
   "type": "Boardgame",
   "bgoId": "2ukSnJ39H9",
   "indiaUrl": "",
   "discount": null,
   "status": "Not Started",
   "prices": {
    "USA": 15.96,
    "UK": 15.96,
    "Canada": 15.96,
    "Australia": 15.96,
    "NZ": 15.96
   },
   "stock": {
    "USA": "In stock",
    "UK": "In stock",
    "Canada": "In stock",
    "Australia": "In stock",
    "NZ": "In stock"
   },
   "india": null
  },
  {
   "name": "Railroad Tiles",
   "type": "Boardgame",
   "bgoId": "s1AVOspq25",
   "indiaUrl": "",
   "discount": null,
   "status": "Not Started",
   "prices": {
    "USA": 31.94,
    "UK": 31.94,
    "Canada": 31.94,
    "Australia": 31.94,
    "NZ": 31.94
   },
   "stock": {
    "USA": "In stock",
    "UK": "In stock",
    "Canada": "In stock",
    "Australia": "In stock",
    "NZ": "In stock"
   },
   "india": null
  },
  {
   "name": "Red Carpet",
   "type": "Boardgame",
   "bgoId": "BFfYlvWS7B",
   "indiaUrl": "",
   "discount": null,
   "status": "Not Started",
   "prices": {
    "USA": 25.99,
    "UK": 25.99,
    "Canada": 25.99,
    "Australia": 25.99,
    "NZ": 25.99
   },
   "stock": {
    "USA": "In stock",
    "UK": "In stock",
    "Canada": "In stock",
    "Australia": "In stock",
    "NZ": "In stock"
   },
   "india": null
  },
  {
   "name": "Sagrada",
   "type": "Boardgame",
   "bgoId": "ivLKpH2qMz",
   "indiaUrl": "",
   "discount": null,
   "status": "Not Started",
   "prices": {
    "USA": 31.96,
    "UK": 31.96,
    "Canada": 31.96,
    "Australia": 31.96,
    "NZ": 31.96
   },
   "stock": {
    "USA": "In stock",
    "UK": "In stock",
    "Canada": "In stock",
    "Australia": "In stock",
    "NZ": "In stock"
   },
   "india": null
  },
  {
   "name": "Santorini",
   "type": "Boardgame",
   "bgoId": "5_TQJXBwtr",
   "indiaUrl": "",
   "discount": null,
   "status": "Not Started",
   "prices": {
    "USA": 49.99,
    "UK": 49.99,
    "Canada": 49.99,
    "Australia": 49.99,
    "NZ": 49.99
   },
   "stock": {
    "USA": "In stock",
    "UK": "In stock",
    "Canada": "In stock",
    "Australia": "In stock",
    "NZ": "In stock"
   },
   "india": null
  },
  {
   "name": "Schotten Totten",
   "type": "Boardgame",
   "bgoId": "AqCS_RGHZK",
   "indiaUrl": "",
   "discount": null,
   "status": "Not Started",
   "prices": {
    "USA": 11.49,
    "UK": 11.49,
    "Canada": 11.49,
    "Australia": 11.49,
    "NZ": 11.49
   },
   "stock": {
    "USA": "In stock",
    "UK": "In stock",
    "Canada": "In stock",
    "Australia": "In stock",
    "NZ": "In stock"
   },
   "india": null
  },
  {
   "name": "Sea Salt & Paper",
   "type": "Boardgame",
   "bgoId": "zNv72j3A63",
   "indiaUrl": "",
   "discount": null,
   "status": "Not Started",
   "prices": {
    "USA": 14.39,
    "UK": 14.39,
    "Canada": 14.39,
    "Australia": 14.39,
    "NZ": 14.39
   },
   "stock": {
    "USA": "In stock",
    "UK": "In stock",
    "Canada": "In stock",
    "Australia": "In stock",
    "NZ": "In stock"
   },
   "india": null
  },
  {
   "name": "Sky Team: Turbulence",
   "type": "Expansion",
   "bgoId": "hPvxv_z-xi",
   "indiaUrl": "",
   "discount": null,
   "status": "Not Started",
   "prices": {
    "USA": 12.99,
    "UK": 12.99,
    "Canada": 12.99,
    "Australia": 12.99,
    "NZ": 12.99
   },
   "stock": {
    "USA": "In stock",
    "UK": "In stock",
    "Canada": "In stock",
    "Australia": "In stock",
    "NZ": "In stock"
   },
   "india": null
  },
  {
   "name": "So Clover!",
   "type": "Boardgame",
   "bgoId": "CwEdM88bNs",
   "indiaUrl": "",
   "discount": null,
   "status": "Not Started",
   "prices": {
    "USA": 22.39,
    "UK": 22.39,
    "Canada": 22.39,
    "Australia": 22.39,
    "NZ": 22.39
   },
   "stock": {
    "USA": "In stock",
    "UK": "In stock",
    "Canada": "In stock",
    "Australia": "In stock",
    "NZ": "In stock"
   },
   "india": null
  },
  {
   "name": "Sobek: 2 Players",
   "type": "Boardgame",
   "bgoId": "12vLrbi1bt",
   "indiaUrl": "",
   "discount": null,
   "status": "Not Started",
   "prices": {
    "USA": 22.46,
    "UK": 22.46,
    "Canada": 22.46,
    "Australia": 22.46,
    "NZ": 22.46
   },
   "stock": {
    "USA": "In stock",
    "UK": "In stock",
    "Canada": "In stock",
    "Australia": "In stock",
    "NZ": "In stock"
   },
   "india": null
  },
  {
   "name": "Spicy",
   "type": "Boardgame",
   "bgoId": "vCmcAk7DaT",
   "indiaUrl": "",
   "discount": null,
   "status": "Not Started",
   "prices": {
    "USA": 15.95,
    "UK": 15.95,
    "Canada": 15.95,
    "Australia": 15.95,
    "NZ": 15.95
   },
   "stock": {
    "USA": "In stock",
    "UK": "In stock",
    "Canada": "In stock",
    "Australia": "In stock",
    "NZ": "In stock"
   },
   "india": null
  },
  {
   "name": "Steampunk Rally Fusion",
   "type": "Boardgame",
   "bgoId": "EhRJfXsJ-X",
   "indiaUrl": "",
   "discount": null,
   "status": "Not Started",
   "prices": {
    "USA": 39.97,
    "UK": 39.97,
    "Canada": 39.97,
    "Australia": 39.97,
    "NZ": 39.97
   },
   "stock": {
    "USA": "In stock",
    "UK": "In stock",
    "Canada": "In stock",
    "Australia": "In stock",
    "NZ": "In stock"
   },
   "india": null
  },
  {
   "name": "Stockpile",
   "type": "Boardgame",
   "bgoId": "TN1kSZMy7h",
   "indiaUrl": "",
   "discount": null,
   "status": "Not Started",
   "prices": {
    "USA": 44.99,
    "UK": 44.99,
    "Canada": 44.99,
    "Australia": 44.99,
    "NZ": 44.99
   },
   "stock": {
    "USA": "Out of stock",
    "UK": "Out of stock",
    "Canada": "Out of stock",
    "Australia": "Out of stock",
    "NZ": "Out of stock"
   },
   "india": null
  },
  {
   "name": "Strike",
   "type": "Boardgame",
   "bgoId": "KjDIQclVIn",
   "indiaUrl": "",
   "discount": null,
   "status": "Not Started",
   "prices": {
    "USA": 19.99,
    "UK": 19.99,
    "Canada": 19.99,
    "Australia": 19.99,
    "NZ": 19.99
   },
   "stock": {
    "USA": "In stock",
    "UK": "In stock",
    "Canada": "In stock",
    "Australia": "In stock",
    "NZ": "In stock"
   },
   "india": null
  },
  {
   "name": "Subjective",
   "type": "Boardgame",
   "bgoId": "kpwx56MSUl",
   "indiaUrl": "",
   "discount": null,
   "status": "Not Started",
   "prices": {
    "USA": 19.99,
    "UK": 19.99,
    "Canada": 19.99,
    "Australia": 19.99,
    "NZ": 19.99
   },
   "stock": {
    "USA": "In stock",
    "UK": "In stock",
    "Canada": "In stock",
    "Australia": "In stock",
    "NZ": "In stock"
   },
   "india": null
  },
  {
   "name": "Suburbia",
   "type": "Boardgame",
   "bgoId": "3rID_z0BVG",
   "indiaUrl": "",
   "discount": null,
   "status": "Not Started",
   "prices": {
    "USA": 50.47,
    "UK": 50.47,
    "Canada": 50.47,
    "Australia": 50.47,
    "NZ": 50.47
   },
   "stock": {
    "USA": "In stock",
    "UK": "In stock",
    "Canada": "In stock",
    "Australia": "In stock",
    "NZ": "In stock"
   },
   "india": null
  },
  {
   "name": "Takenoko",
   "type": "Boardgame",
   "bgoId": "UfustagRW2",
   "indiaUrl": "",
   "discount": null,
   "status": "Not Started",
   "prices": {
    "USA": 43.99,
    "UK": 43.99,
    "Canada": 43.99,
    "Australia": 43.99,
    "NZ": 43.99
   },
   "stock": {
    "USA": "In stock",
    "UK": "In stock",
    "Canada": "In stock",
    "Australia": "In stock",
    "NZ": "In stock"
   },
   "india": null
  },
  {
   "name": "TEAM3 GREEN",
   "type": "Boardgame",
   "bgoId": "lAzkD15FfY",
   "indiaUrl": "",
   "discount": null,
   "status": "Not Started",
   "prices": {
    "USA": 14.97,
    "UK": 14.97,
    "Canada": 14.97,
    "Australia": 14.97,
    "NZ": 14.97
   },
   "stock": {
    "USA": "Out of stock",
    "UK": "Out of stock",
    "Canada": "Out of stock",
    "Australia": "Out of stock",
    "NZ": "Out of stock"
   },
   "india": null
  },
  {
   "name": "TEAM3 PINK",
   "type": "Boardgame",
   "bgoId": "Hrum0uJlnj",
   "indiaUrl": "",
   "discount": null,
   "status": "Not Started",
   "prices": {
    "USA": 16.99,
    "UK": 16.99,
    "Canada": 16.99,
    "Australia": 16.99,
    "NZ": 16.99
   },
   "stock": {
    "USA": "Out of stock",
    "UK": "Out of stock",
    "Canada": "Out of stock",
    "Australia": "Out of stock",
    "NZ": "Out of stock"
   },
   "india": null
  },
  {
   "name": "Terraforming Mars: Ares Expedition",
   "type": "Boardgame",
   "bgoId": "8u88FlblU7",
   "indiaUrl": "",
   "discount": null,
   "status": "Not Started",
   "prices": {
    "USA": 28.99,
    "UK": 28.99,
    "Canada": 28.99,
    "Australia": 28.99,
    "NZ": 28.99
   },
   "stock": {
    "USA": "In stock",
    "UK": "In stock",
    "Canada": "In stock",
    "Australia": "In stock",
    "NZ": "In stock"
   },
   "india": null
  },
  {
   "name": "That's Not a Hat: Pop Culture",
   "type": "Boardgame",
   "bgoId": "VRY69G3nCF",
   "indiaUrl": "",
   "discount": null,
   "status": "Not Started",
   "prices": {
    "USA": 9.97,
    "UK": 9.97,
    "Canada": 9.97,
    "Australia": 9.97,
    "NZ": 9.97
   },
   "stock": {
    "USA": "In stock",
    "UK": "In stock",
    "Canada": "In stock",
    "Australia": "In stock",
    "NZ": "In stock"
   },
   "india": null
  },
  {
   "name": "The Castles of Burgundy",
   "type": "Boardgame",
   "bgoId": "X0x0v2_TzQ",
   "indiaUrl": "",
   "discount": null,
   "status": "Not Started",
   "prices": {
    "USA": 26.99,
    "UK": 26.99,
    "Canada": 26.99,
    "Australia": 26.99,
    "NZ": 26.99
   },
   "stock": {
    "USA": "Out of stock",
    "UK": "Out of stock",
    "Canada": "Out of stock",
    "Australia": "Out of stock",
    "NZ": "Out of stock"
   },
   "india": null
  },
  {
   "name": "The LOOP: Fur Brigade",
   "type": "Expansion",
   "bgoId": "edv2UMAKvU",
   "indiaUrl": "",
   "discount": null,
   "status": "Not Started",
   "prices": {
    "USA": 14.97,
    "UK": 14.97,
    "Canada": 14.97,
    "Australia": 14.97,
    "NZ": 14.97
   },
   "stock": {
    "USA": "Out of stock",
    "UK": "Out of stock",
    "Canada": "Out of stock",
    "Australia": "Out of stock",
    "NZ": "Out of stock"
   },
   "india": null
  },
  {
   "name": "The LOOP: The Revenge of Fauxzilla",
   "type": "Expansion",
   "bgoId": "ZKnU2XWIWv",
   "indiaUrl": "",
   "discount": null,
   "status": "Not Started",
   "prices": {
    "USA": 18.97,
    "UK": 18.97,
    "Canada": 18.97,
    "Australia": 18.97,
    "NZ": 18.97
   },
   "stock": {
    "USA": "Out of stock",
    "UK": "Out of stock",
    "Canada": "Out of stock",
    "Australia": "Out of stock",
    "NZ": "Out of stock"
   },
   "india": null
  },
  {
   "name": "The Office: Paper Paranoia",
   "type": "Boardgame",
   "bgoId": "KdaasWEzJu",
   "indiaUrl": "",
   "discount": null,
   "status": "Not Started",
   "prices": {
    "USA": 28.99,
    "UK": 28.99,
    "Canada": 28.99,
    "Australia": 28.99,
    "NZ": 28.99
   },
   "stock": {
    "USA": "In stock",
    "UK": "In stock",
    "Canada": "In stock",
    "Australia": "In stock",
    "NZ": "In stock"
   },
   "india": null
  },
  {
   "name": "The Shipwreck Arcana",
   "type": "Boardgame",
   "bgoId": "7l51E2FScr",
   "indiaUrl": "",
   "discount": null,
   "status": "Not Started",
   "prices": {
    "USA": 27.95,
    "UK": 27.95,
    "Canada": 27.95,
    "Australia": 27.95,
    "NZ": 27.95
   },
   "stock": {
    "USA": "In stock",
    "UK": "In stock",
    "Canada": "In stock",
    "Australia": "In stock",
    "NZ": "In stock"
   },
   "india": null
  },
  {
   "name": "Thunder Road: Vendetta",
   "type": "Boardgame",
   "bgoId": "2rfvo_VuSG",
   "indiaUrl": "",
   "discount": null,
   "status": "Not Started",
   "prices": {
    "USA": 44.97,
    "UK": 44.97,
    "Canada": 44.97,
    "Australia": 44.97,
    "NZ": 44.97
   },
   "stock": {
    "USA": "In stock",
    "UK": "In stock",
    "Canada": "In stock",
    "Australia": "In stock",
    "NZ": "In stock"
   },
   "india": null
  },
  {
   "name": "Trial by Trolley: Derailed Edition",
   "type": "Expansion",
   "bgoId": "7eitnp0UdM",
   "indiaUrl": "",
   "discount": null,
   "status": "Not Started",
   "prices": {
    "USA": null,
    "UK": null,
    "Canada": null,
    "Australia": null,
    "NZ": null
   },
   "stock": {
    "USA": "",
    "UK": "",
    "Canada": "",
    "Australia": "",
    "NZ": ""
   },
   "india": null
  },
  {
   "name": "Trial by Trolley: Kickstarter Expansion",
   "type": "Expansion",
   "bgoId": "JZ2eTvnCxp",
   "indiaUrl": "",
   "discount": null,
   "status": "Not Started",
   "prices": {
    "USA": null,
    "UK": null,
    "Canada": null,
    "Australia": null,
    "NZ": null
   },
   "stock": {
    "USA": "",
    "UK": "",
    "Canada": "",
    "Australia": "",
    "NZ": ""
   },
   "india": null
  },
  {
   "name": "Trial by Trolley: R-Rated Modifier Expansion",
   "type": "Expansion",
   "bgoId": "TEnTcmm1i9",
   "indiaUrl": "",
   "discount": null,
   "status": "Not Started",
   "prices": {
    "USA": 11.47,
    "UK": 11.47,
    "Canada": 11.47,
    "Australia": 11.47,
    "NZ": 11.47
   },
   "stock": {
    "USA": "In stock",
    "UK": "In stock",
    "Canada": "In stock",
    "Australia": "In stock",
    "NZ": "In stock"
   },
   "india": null
  },
  {
   "name": "Trial by Trolley: R-Rated Track Expansion",
   "type": "Expansion",
   "bgoId": "B5jEifX75k",
   "indiaUrl": "",
   "discount": null,
   "status": "Not Started",
   "prices": {
    "USA": 11.47,
    "UK": 11.47,
    "Canada": 11.47,
    "Australia": 11.47,
    "NZ": 11.47
   },
   "stock": {
    "USA": "In stock",
    "UK": "In stock",
    "Canada": "In stock",
    "Australia": "In stock",
    "NZ": "In stock"
   },
   "india": null
  },
  {
   "name": "Trial By Trolley: Vacation Expansion",
   "type": "Expansion",
   "bgoId": "aGxtTX51wj",
   "indiaUrl": "",
   "discount": null,
   "status": "Not Started",
   "prices": {
    "USA": null,
    "UK": null,
    "Canada": null,
    "Australia": 19.95,
    "NZ": 39
   },
   "stock": {
    "USA": "",
    "UK": "",
    "Canada": "",
    "Australia": "In stock",
    "NZ": "In stock"
   },
   "india": null
  },
  {
   "name": "Unstable Unicorns: Dragons Expansion Pack",
   "type": "Expansion",
   "bgoId": "S9IeODA7ad",
   "indiaUrl": "",
   "discount": null,
   "status": "Not Started",
   "prices": {
    "USA": 12.63,
    "UK": 12.63,
    "Canada": 12.63,
    "Australia": 12.63,
    "NZ": 12.63
   },
   "stock": {
    "USA": "In stock",
    "UK": "In stock",
    "Canada": "In stock",
    "Australia": "In stock",
    "NZ": "In stock"
   },
   "india": null
  },
  {
   "name": "Unstable Unicorns: NSFW Pack",
   "type": "Expansion",
   "bgoId": "eDxco3NhB0",
   "indiaUrl": "",
   "discount": null,
   "status": "Not Started",
   "prices": {
    "USA": 24.96,
    "UK": 24.96,
    "Canada": 24.96,
    "Australia": 24.96,
    "NZ": 24.96
   },
   "stock": {
    "USA": "In stock",
    "UK": "In stock",
    "Canada": "In stock",
    "Australia": "In stock",
    "NZ": "In stock"
   },
   "india": null
  },
  {
   "name": "Unstable Unicorns: Rainbow Apocalypse Expansion Pack",
   "type": "Expansion",
   "bgoId": "yr_EYtPFMb",
   "indiaUrl": "",
   "discount": null,
   "status": "Not Started",
   "prices": {
    "USA": 12.63,
    "UK": 12.63,
    "Canada": 12.63,
    "Australia": 12.63,
    "NZ": 12.63
   },
   "stock": {
    "USA": "In stock",
    "UK": "In stock",
    "Canada": "In stock",
    "Australia": "In stock",
    "NZ": "In stock"
   },
   "india": null
  },
  {
   "name": "Unstable Unicorns: Unicorns of Legend Expansion Pack",
   "type": "Expansion",
   "bgoId": "QkItIkQWst",
   "indiaUrl": "",
   "discount": null,
   "status": "Not Started",
   "prices": {
    "USA": 12.63,
    "UK": 12.63,
    "Canada": 12.63,
    "Australia": 12.63,
    "NZ": 12.63
   },
   "stock": {
    "USA": "In stock",
    "UK": "In stock",
    "Canada": "In stock",
    "Australia": "In stock",
    "NZ": "In stock"
   },
   "india": null
  },
  {
   "name": "Unstoppable",
   "type": "Boardgame",
   "bgoId": "7wWaP8A8TF",
   "indiaUrl": "",
   "discount": null,
   "status": "Not Started",
   "prices": {
    "USA": 59.99,
    "UK": 59.99,
    "Canada": 59.99,
    "Australia": 59.99,
    "NZ": 59.99
   },
   "stock": {
    "USA": "In stock",
    "UK": "In stock",
    "Canada": "In stock",
    "Australia": "In stock",
    "NZ": "In stock"
   },
   "india": null
  },
  {
   "name": "Western Legends",
   "type": "Boardgame",
   "bgoId": "8xCkyLhdEr",
   "indiaUrl": "",
   "discount": null,
   "status": "Not Started",
   "prices": {
    "USA": 58.73,
    "UK": 58.73,
    "Canada": 58.73,
    "Australia": 58.73,
    "NZ": 58.73
   },
   "stock": {
    "USA": "In stock",
    "UK": "In stock",
    "Canada": "In stock",
    "Australia": "In stock",
    "NZ": "In stock"
   },
   "india": null
  },
  {
   "name": "Wingspan",
   "type": "Boardgame",
   "bgoId": "1cF2LLZC_o",
   "indiaUrl": "https://www.boardgamesindia.com/wingspan-with-swift-start-pack",
   "discount": null,
   "status": "Not Started",
   "prices": {
    "USA": 55,
    "UK": 55,
    "Canada": 55,
    "Australia": 55,
    "NZ": 55
   },
   "stock": {
    "USA": "In stock",
    "UK": "In stock",
    "Canada": "In stock",
    "Australia": "In stock",
    "NZ": "In stock"
   },
   "india": {
    "price": 5500,
    "source": "Board Games India",
    "stock": "In stock"
   }
  },
  {
   "name": "Wingspan Asia",
   "type": "Boardgame",
   "bgoId": "ijObtUSyVq",
   "indiaUrl": "",
   "discount": null,
   "status": "Not Started",
   "prices": {
    "USA": 36,
    "UK": 36,
    "Canada": 36,
    "Australia": 36,
    "NZ": 36
   },
   "stock": {
    "USA": "In stock",
    "UK": "In stock",
    "Canada": "In stock",
    "Australia": "In stock",
    "NZ": "In stock"
   },
   "india": null
  },
  {
   "name": "Staccs",
   "type": "Boardgame",
   "bgoId": "",
   "indiaUrl": "",
   "discount": null,
   "status": "Not Started",
   "prices": {
    "USA": null,
    "UK": null,
    "Canada": null,
    "Australia": null,
    "NZ": null
   },
   "stock": {
    "USA": null,
    "UK": null,
    "Canada": null,
    "Australia": null,
    "NZ": null
   },
   "india": null
  },
  {
   "name": "This bed is mine",
   "type": "Boardgame",
   "bgoId": "",
   "indiaUrl": "",
   "discount": null,
   "status": "Not Started",
   "prices": {
    "USA": null,
    "UK": null,
    "Canada": null,
    "Australia": null,
    "NZ": null
   },
   "stock": {
    "USA": null,
    "UK": null,
    "Canada": null,
    "Australia": null,
    "NZ": null
   },
   "india": null
  },
  {
   "name": "Wroth",
   "type": "Boardgame",
   "bgoId": "smRN03CKdQ",
   "indiaUrl": "",
   "discount": null,
   "status": "Not Started",
   "prices": {
    "USA": 64.95,
    "UK": 64.95,
    "Canada": 64.95,
    "Australia": 64.95,
    "NZ": 64.95
   },
   "stock": {
    "USA": "In stock",
    "UK": "In stock",
    "Canada": "In stock",
    "Australia": "In stock",
    "NZ": "In stock"
   },
   "india": null
  },
  {
   "name": "Magical athlete",
   "type": "Boardgame",
   "bgoId": "zk2NFLfgzB",
   "indiaUrl": "",
   "discount": null,
   "status": "Not Started",
   "prices": {
    "USA": 26.99,
    "UK": 26.99,
    "Canada": 26.99,
    "Australia": 26.99,
    "NZ": 26.99
   },
   "stock": {
    "USA": "In stock",
    "UK": "In stock",
    "Canada": "In stock",
    "Australia": "In stock",
    "NZ": "In stock"
   },
   "india": null
  },
  {
   "name": "Viticulture",
   "type": "Boardgame",
   "bgoId": "XZMHLFoIoR",
   "indiaUrl": "",
   "discount": null,
   "status": "Not Started",
   "prices": {
    "USA": null,
    "UK": null,
    "Canada": null,
    "Australia": null,
    "NZ": 143.95
   },
   "stock": {
    "USA": "",
    "UK": "",
    "Canada": "",
    "Australia": "",
    "NZ": "In stock"
   },
   "india": null
  },
  {
   "name": "Hot streak",
   "type": "Boardgame",
   "bgoId": "8QsoE29eTQ",
   "indiaUrl": "",
   "discount": null,
   "status": "Not Started",
   "prices": {
    "USA": 44.99,
    "UK": 44.99,
    "Canada": 44.99,
    "Australia": 44.99,
    "NZ": 44.99
   },
   "stock": {
    "USA": "In stock",
    "UK": "In stock",
    "Canada": "In stock",
    "Australia": "In stock",
    "NZ": "In stock"
   },
   "india": null
  },
  {
   "name": "Bang! The Dice Game",
   "type": "Boardgame",
   "bgoId": "R-pmk1K5GM",
   "indiaUrl": "",
   "discount": null,
   "status": "Not Started",
   "prices": {
    "USA": 14.39,
    "UK": 14.39,
    "Canada": 14.39,
    "Australia": 14.39,
    "NZ": 14.39
   },
   "stock": {
    "USA": "In stock",
    "UK": "In stock",
    "Canada": "In stock",
    "Australia": "In stock",
    "NZ": "In stock"
   },
   "india": null
  },
  {
   "name": "Jibber jabble",
   "type": "Boardgame",
   "bgoId": "GgHoKI07lj",
   "indiaUrl": "",
   "discount": null,
   "status": "Not Started",
   "prices": {
    "USA": null,
    "UK": null,
    "Canada": null,
    "Australia": 15.95,
    "NZ": null
   },
   "stock": {
    "USA": "",
    "UK": "",
    "Canada": "",
    "Australia": "In stock",
    "NZ": ""
   },
   "india": null
  },
  {
   "name": "Pinched",
   "type": "Boardgame",
   "bgoId": "cWqQCJmOjh",
   "indiaUrl": "",
   "discount": null,
   "status": "Not Started",
   "prices": {
    "USA": 28,
    "UK": 28,
    "Canada": 28,
    "Australia": 28,
    "NZ": 28
   },
   "stock": {
    "USA": "In stock",
    "UK": "In stock",
    "Canada": "In stock",
    "Australia": "In stock",
    "NZ": "In stock"
   },
   "india": null
  },
  {
   "name": "Solstis",
   "type": "Boardgame",
   "bgoId": "3eEAif5GCH",
   "indiaUrl": "",
   "discount": null,
   "status": "Not Started",
   "prices": {
    "USA": 14.45,
    "UK": 14.45,
    "Canada": 14.45,
    "Australia": 14.45,
    "NZ": 14.45
   },
   "stock": {
    "USA": "In stock",
    "UK": "In stock",
    "Canada": "In stock",
    "Australia": "In stock",
    "NZ": "In stock"
   },
   "india": null
  },
  {
   "name": "Skull King",
   "type": "Boardgame",
   "bgoId": "nWQ3P8Ufah",
   "indiaUrl": "",
   "discount": null,
   "status": "Not Started",
   "prices": {
    "USA": 15.99,
    "UK": 15.99,
    "Canada": 15.99,
    "Australia": 15.99,
    "NZ": 15.99
   },
   "stock": {
    "USA": "In stock",
    "UK": "In stock",
    "Canada": "In stock",
    "Australia": "In stock",
    "NZ": "In stock"
   },
   "india": null
  },
  {
   "name": "Fliptoons",
   "type": "Boardgame",
   "bgoId": "rxRjQF8i3D",
   "indiaUrl": "",
   "discount": null,
   "status": "Not Started",
   "prices": {
    "USA": 14.97,
    "UK": 14.97,
    "Canada": 14.97,
    "Australia": 14.97,
    "NZ": 14.97
   },
   "stock": {
    "USA": "In stock",
    "UK": "In stock",
    "Canada": "In stock",
    "Australia": "In stock",
    "NZ": "In stock"
   },
   "india": null
  },
  {
   "name": "A carnivore did it",
   "type": "Boardgame",
   "bgoId": "pWoZk0MByb",
   "indiaUrl": "",
   "discount": null,
   "status": "Not Started",
   "prices": {
    "USA": 14.44,
    "UK": 14.44,
    "Canada": 14.44,
    "Australia": 14.44,
    "NZ": 14.44
   },
   "stock": {
    "USA": "Out of stock",
    "UK": "Out of stock",
    "Canada": "Out of stock",
    "Australia": "Out of stock",
    "NZ": "Out of stock"
   },
   "india": null
  },
  {
   "name": "Ruins",
   "type": "Boardgame",
   "bgoId": "IFiJrANmW5",
   "indiaUrl": "",
   "discount": null,
   "status": "Not Started",
   "prices": {
    "USA": 15.99,
    "UK": 15.99,
    "Canada": 15.99,
    "Australia": 15.99,
    "NZ": 15.99
   },
   "stock": {
    "USA": "In stock",
    "UK": "In stock",
    "Canada": "In stock",
    "Australia": "In stock",
    "NZ": "In stock"
   },
   "india": null
  },
  {
   "name": "Petiquette",
   "type": "Boardgame",
   "bgoId": "47FSVFT3HA",
   "indiaUrl": "",
   "discount": null,
   "status": "Not Started",
   "prices": {
    "USA": 16.79,
    "UK": 16.79,
    "Canada": 16.79,
    "Australia": 16.79,
    "NZ": 16.79
   },
   "stock": {
    "USA": "In stock",
    "UK": "In stock",
    "Canada": "In stock",
    "Australia": "In stock",
    "NZ": "In stock"
   },
   "india": null
  },
  {
   "name": "Popcorn",
   "type": "Boardgame",
   "bgoId": "JAZXxHb1mI",
   "indiaUrl": "",
   "discount": null,
   "status": "Not Started",
   "prices": {
    "USA": null,
    "UK": 11.99,
    "Canada": null,
    "Australia": null,
    "NZ": null
   },
   "stock": {
    "USA": "",
    "UK": "In stock",
    "Canada": "",
    "Australia": "",
    "NZ": ""
   },
   "india": null
  },
  {
   "name": "Durian",
   "type": "Boardgame",
   "bgoId": "o2dheOH4DS",
   "indiaUrl": "",
   "discount": null,
   "status": "Not Started",
   "prices": {
    "USA": 16.97,
    "UK": 16.97,
    "Canada": 16.97,
    "Australia": 16.97,
    "NZ": 16.97
   },
   "stock": {
    "USA": "In stock",
    "UK": "In stock",
    "Canada": "In stock",
    "Australia": "In stock",
    "NZ": "In stock"
   },
   "india": null
  },
  {
   "name": "Radlands",
   "type": "Boardgame",
   "bgoId": "OKtz5PXOuM",
   "indiaUrl": "",
   "discount": null,
   "status": "Not Started",
   "prices": {
    "USA": 24.99,
    "UK": 24.99,
    "Canada": 24.99,
    "Australia": 24.99,
    "NZ": 24.99
   },
   "stock": {
    "USA": "In stock",
    "UK": "In stock",
    "Canada": "In stock",
    "Australia": "In stock",
    "NZ": "In stock"
   },
   "india": null
  },
  {
   "name": "Bank Heist",
   "type": "Boardgame",
   "bgoId": "",
   "indiaUrl": "",
   "discount": null,
   "status": "Not Started",
   "prices": {
    "USA": null,
    "UK": null,
    "Canada": null,
    "Australia": null,
    "NZ": null
   },
   "stock": {
    "USA": null,
    "UK": null,
    "Canada": null,
    "Australia": null,
    "NZ": null
   },
   "india": null
  },
  {
   "name": "Pool party",
   "type": "Boardgame",
   "bgoId": "SUfRKlT___",
   "indiaUrl": "",
   "discount": null,
   "status": "Not Started",
   "prices": {
    "USA": 15.99,
    "UK": 15.99,
    "Canada": 15.99,
    "Australia": 15.99,
    "NZ": 15.99
   },
   "stock": {
    "USA": "In stock",
    "UK": "In stock",
    "Canada": "In stock",
    "Australia": "In stock",
    "NZ": "In stock"
   },
   "india": null
  },
  {
   "name": "Collect",
   "type": "Boardgame",
   "bgoId": "40AH8ardB7",
   "indiaUrl": "",
   "discount": null,
   "status": "Not Started",
   "prices": {
    "USA": null,
    "UK": null,
    "Canada": null,
    "Australia": null,
    "NZ": null
   },
   "stock": {
    "USA": "",
    "UK": "",
    "Canada": "",
    "Australia": "",
    "NZ": ""
   },
   "india": null
  },
  {
   "name": "K3",
   "type": "Boardgame",
   "bgoId": "IKK5nG55w6",
   "indiaUrl": "",
   "discount": null,
   "status": "Not Started",
   "prices": {
    "USA": 21.95,
    "UK": 21.95,
    "Canada": 21.95,
    "Australia": 21.95,
    "NZ": 21.95
   },
   "stock": {
    "USA": "In stock",
    "UK": "In stock",
    "Canada": "In stock",
    "Australia": "In stock",
    "NZ": "In stock"
   },
   "india": null
  },
  {
   "name": "Catan",
   "type": "Boardgame",
   "bgoId": "04ACtDMij8",
   "indiaUrl": "",
   "discount": null,
   "status": "Not Started",
   "prices": {
    "USA": 39.47,
    "UK": 39.47,
    "Canada": 39.47,
    "Australia": 39.47,
    "NZ": 39.47
   },
   "stock": {
    "USA": "In stock",
    "UK": "In stock",
    "Canada": "In stock",
    "Australia": "In stock",
    "NZ": "In stock"
   },
   "india": null
  },
  {
   "name": "Legacy of Yu",
   "type": "Boardgame",
   "bgoId": "vmH2xJcMgd",
   "indiaUrl": "",
   "discount": null,
   "status": "Not Started",
   "prices": {
    "USA": 59.99,
    "UK": 59.99,
    "Canada": 59.99,
    "Australia": 59.99,
    "NZ": 59.99
   },
   "stock": {
    "USA": "In stock",
    "UK": "In stock",
    "Canada": "In stock",
    "Australia": "In stock",
    "NZ": "In stock"
   },
   "india": null
  }
 ]
}